spinn_utilities/__init__.py
spinn_utilities/_version.py
spinn_utilities/abstract_base.py
spinn_utilities/abstract_context_manager.py
spinn_utilities/bytestring_utils.py
spinn_utilities/classproperty.py
spinn_utilities/conf_loader.py
spinn_utilities/config_holder.py
spinn_utilities/config_setup.py
spinn_utilities/exceptions.py
spinn_utilities/executable_finder.py
spinn_utilities/find_max_success.py
spinn_utilities/helpful_functions.py
spinn_utilities/log.py
spinn_utilities/log_store.py
spinn_utilities/logger_utils.py
spinn_utilities/ordered_set.py
spinn_utilities/overrides.py
spinn_utilities/package_loader.py
spinn_utilities/ping.py
spinn_utilities/progress_bar.py
spinn_utilities/py.typed
spinn_utilities/require_subclass.py
spinn_utilities/safe_eval.py
spinn_utilities/socket_address.py
spinn_utilities/spinn_utilities.cfg
spinn_utilities/timer.py
spinn_utilities/citation/__init__.py
spinn_utilities/citation/citation_aggregator.py
spinn_utilities/citation/citation_updater_and_doi_generator.py
spinn_utilities/configs/__init__.py
spinn_utilities/configs/camel_case_config_parser.py
spinn_utilities/configs/config_checker.py
spinn_utilities/configs/config_documentor.py
spinn_utilities/configs/config_template_exception.py
spinn_utilities/configs/no_config_found_exception.py
spinn_utilities/configs/notes.md
spinn_utilities/configs/two_user_configs_exception.py
spinn_utilities/configs/unexpected_config_exception.py
spinn_utilities/data/__init__.py
spinn_utilities/data/data_status.py
spinn_utilities/data/reset_status.py
spinn_utilities/data/run_status.py
spinn_utilities/data/utils_data_view.py
spinn_utilities/data/utils_data_writer.py
spinn_utilities/make_tools/__init__.py
spinn_utilities/make_tools/converter.py
spinn_utilities/make_tools/db.sql
spinn_utilities/make_tools/file_converter.py
spinn_utilities/make_tools/log_sqllite_database.py
spinn_utilities/make_tools/logs.sqlite3
spinn_utilities/make_tools/replacer.py
spinn_utilities/ranged/__init__.py
spinnutilities-1!7.4.0.dist-info/licenses/LICENSE
spinnutilities-1!7.4.0.dist-info/licenses/LICENSE_POLICY.md
spinnutilities-1!7.4.0.dist-info/METADATA
spinnutilities-1!7.4.0.dist-info/WHEEL
spinnutilities-1!7.4.0.dist-info/top_level.txt
spinnutilities-1!7.4.0.dist-info/zip-safe
spinnutilities-1!7.4.0.dist-info/RECORD
